[{"year": 104, "month": 3, "issue": "104000018", "drawDate": "104/03/02", "redeemDate": "104/06/02", "numbersInBlock1": ["09", "11", "12", "21", "31", "36"], "numbersInBlock2": "07"}, {"year": 104, "month": 3, "issue": "104000019", "drawDate": "104/03/05", "redeemDate": "104/06/05", "numbersInBlock1": ["02", "04", "08", "13", "24", "26"], "numbersInBlock2": "02"}, {"year": 104, "month": 3, "issue": "104000020", "drawDate": "104/03/09", "redeemDate": "104/06/09", "numbersInBlock1": ["03", "12", "16", "18", "21", "36"], "numbersInBlock2": "03"}, {"year": 104, "month": 3, "issue": "104000021", "drawDate": "104/03/12", "redeemDate": "104/06/12", "numbersInBlock1": ["01", "02", "14", "22", "27", "30"], "numbersInBlock2": "01"}, {"year": 104, "month": 3, "issue": "104000022", "drawDate": "104/03/16", "redeemDate": "104/06/16", "numbersInBlock1": ["05", "08", "20", "22", "30", "34"], "numbersInBlock2": "08"}, {"year": 104, "month": 3, "issue": "104000023", "drawDate": "104/03/19", "redeemDate": "104/06/22", "numbersInBlock1": ["06", "17", "30", "34", "35", "38"], "numbersInBlock2": "02"}, {"year": 104, "month": 3, "issue": "104000024", "drawDate": "104/03/23", "redeemDate": "104/06/23", "numbersInBlock1": ["10", "12", "17", "18", "27", "32"], "numbersInBlock2": "05"}, {"year": 104, "month": 3, "issue": "104000025", "drawDate": "104/03/26", "redeemDate": "104/06/26", "numbersInBlock1": ["06", "14", "24", "26", "36", "38"], "numbersInBlock2": "03"}, {"year": 104, "month": 3, "issue": "104000026", "drawDate": "104/03/30", "redeemDate": "104/06/30", "numbersInBlock1": ["01", "08", "10", "19", "23", "24"], "numbersInBlock2": "05"}]