[{"year": 107, "month": 5, "issue": "107000036", "drawDate": "107/05/03", "redeemDate": "107/08/03", "numbersInBlock1": ["06", "09", "10", "12", "18", "26"], "numbersInBlock2": "05"}, {"year": 107, "month": 5, "issue": "107000037", "drawDate": "107/05/07", "redeemDate": "107/08/07", "numbersInBlock1": ["05", "08", "15", "28", "33", "35"], "numbersInBlock2": "06"}, {"year": 107, "month": 5, "issue": "107000038", "drawDate": "107/05/10", "redeemDate": "107/08/10", "numbersInBlock1": ["08", "09", "13", "18", "22", "36"], "numbersInBlock2": "08"}, {"year": 107, "month": 5, "issue": "107000039", "drawDate": "107/05/14", "redeemDate": "107/08/14", "numbersInBlock1": ["05", "12", "27", "30", "32", "37"], "numbersInBlock2": "07"}, {"year": 107, "month": 5, "issue": "107000040", "drawDate": "107/05/17", "redeemDate": "107/08/17", "numbersInBlock1": ["10", "11", "17", "22", "24", "38"], "numbersInBlock2": "04"}, {"year": 107, "month": 5, "issue": "107000041", "drawDate": "107/05/21", "redeemDate": "107/08/21", "numbersInBlock1": ["04", "07", "16", "21", "35", "36"], "numbersInBlock2": "01"}, {"year": 107, "month": 5, "issue": "107000042", "drawDate": "107/05/24", "redeemDate": "107/08/29", "numbersInBlock1": ["05", "15", "22", "24", "29", "38"], "numbersInBlock2": "08"}, {"year": 107, "month": 5, "issue": "107000043", "drawDate": "107/05/28", "redeemDate": "107/08/29", "numbersInBlock1": ["09", "12", "14", "20", "26", "32"], "numbersInBlock2": "06"}, {"year": 107, "month": 5, "issue": "107000044", "drawDate": "107/05/31", "redeemDate": "107/08/31", "numbersInBlock1": ["02", "03", "13", "23", "26", "38"], "numbersInBlock2": "07"}]